credict/__init__.py
credict/api.py
credict/encryption.py
credict/math.py
credict/watermark.py
credict-0.1.2.dist-info/METADATA
credict-0.1.2.dist-info/WHEEL
credict-0.1.2.dist-info/top_level.txt
credict-0.1.2.dist-info/RECORD
